zit/__init__.py
zit/auth.py
zit/config.py
zit/dashboard.py
zit/dataset/__init__.py
zit/dataset/build.py
zit/dataset/convert.py
zit/dataset/factory.py
zit/dataset/manager.py
zit/example.py
zit/formula.py
zit/main.py
zit/routes/__init__.py
zit/routes/dataset/annotations.py
zit/routes/dataset/categories.py
zit/routes/dataset/images.py
zit/routes/dataset/queries.py
zit/utils.py
zit-0.0.3.dist-info/METADATA
zit-0.0.3.dist-info/WHEEL
zit-0.0.3.dist-info/entry_points.txt
zit-0.0.3.dist-info/RECORD
