Metadata-Version: 2.1
Name: zit
Version: 0.0.3
Summary: ZitySpace CLI tool
License: MIT
Author: Rui Zheng
Author-email: rui@zityspace.com
Requires-Python: >=3.9,<4.0
Classifier: License :: OSI Approved :: MIT License
Classifier: Programming Language :: Python :: 3
Classifier: Programming Language :: Python :: 3.9
Classifier: Programming Language :: Python :: 3.10
Classifier: Programming Language :: Python :: 3.11
Requires-Dist: PyYAML (>=6.0,<7.0)
Requires-Dist: duckdb (>=0.8.1,<0.9.0)
Requires-Dist: fastapi (>=0.95.1,<0.96.0)
Requires-Dist: httpx[socks] (>=0.24.1,<0.25.0)
Requires-Dist: pandas (>=2.0.2,<3.0.0)
Requires-Dist: pillow (>=9.5.0,<10.0.0)
Requires-Dist: python-multipart (>=0.0.6,<0.0.7)
Requires-Dist: typer[all] (>=0.7.0,<0.8.0)
Requires-Dist: websocket-client (>=1.5.1,<2.0.0)
